loci_checkmarx/__init__.py
loci_checkmarx/main.py
loci_checkmarx/run.py
loci_checkmarx/summary.py
loci_checkmarx/utils.py
loci_checkmarx-0.4.0.dist-info/LICENSE
loci_checkmarx-0.4.0.dist-info/METADATA
loci_checkmarx-0.4.0.dist-info/WHEEL
loci_checkmarx-0.4.0.dist-info/entry_points.txt
loci_checkmarx-0.4.0.dist-info/top_level.txt
loci_checkmarx-0.4.0.dist-info/RECORD
