Metadata-Version: 2.1
Name: loci-checkmarx
Version: 0.4.0
Summary: The official Loci Notes Checkmarx results importer.
Home-page: https://gitlab.com/loci-notes/loci-checkmarx
Author: TheTwitchy
Author-email: thetwitchy@thetwitchy.com
License: UNKNOWN
Platform: UNKNOWN
License-File: LICENSE
Requires-Dist: click
Requires-Dist: requests
Requires-Dist: rich
Requires-Dist: defusedxml
